odoo/addons/fieldservice_skill/README.rst
odoo/addons/fieldservice_skill/__init__.py
odoo/addons/fieldservice_skill/__manifest__.py
odoo/addons/fieldservice_skill/i18n/de.po
odoo/addons/fieldservice_skill/i18n/es.po
odoo/addons/fieldservice_skill/i18n/es_AR.po
odoo/addons/fieldservice_skill/i18n/es_CL.po
odoo/addons/fieldservice_skill/i18n/fieldservice_skill.pot
odoo/addons/fieldservice_skill/i18n/it.po
odoo/addons/fieldservice_skill/i18n/pt_BR.po
odoo/addons/fieldservice_skill/models/__init__.py
odoo/addons/fieldservice_skill/models/fsm_category.py
odoo/addons/fieldservice_skill/models/fsm_order.py
odoo/addons/fieldservice_skill/models/fsm_person.py
odoo/addons/fieldservice_skill/models/fsm_person_skill.py
odoo/addons/fieldservice_skill/models/fsm_template.py
odoo/addons/fieldservice_skill/models/hr_skill.py
odoo/addons/fieldservice_skill/readme/CONFIGURE.md
odoo/addons/fieldservice_skill/readme/CONTRIBUTORS.md
odoo/addons/fieldservice_skill/readme/CREDITS.md
odoo/addons/fieldservice_skill/readme/DESCRIPTION.md
odoo/addons/fieldservice_skill/readme/ROADMAP.md
odoo/addons/fieldservice_skill/readme/USAGE.md
odoo/addons/fieldservice_skill/security/ir.model.access.csv
odoo/addons/fieldservice_skill/static/description/icon.png
odoo/addons/fieldservice_skill/static/description/index.html
odoo/addons/fieldservice_skill/tests/__init__.py
odoo/addons/fieldservice_skill/tests/test_fsm_skill.py
odoo/addons/fieldservice_skill/views/fsm_category.xml
odoo/addons/fieldservice_skill/views/fsm_order.xml
odoo/addons/fieldservice_skill/views/fsm_person.xml
odoo/addons/fieldservice_skill/views/fsm_person_skill.xml
odoo/addons/fieldservice_skill/views/fsm_template.xml
odoo/addons/fieldservice_skill/views/hr_skill.xml
odoo_addon_fieldservice_skill-18.0.1.0.0.2.dist-info/METADATA
odoo_addon_fieldservice_skill-18.0.1.0.0.2.dist-info/WHEEL
odoo_addon_fieldservice_skill-18.0.1.0.0.2.dist-info/top_level.txt
odoo_addon_fieldservice_skill-18.0.1.0.0.2.dist-info/RECORD
